README.rst
setup.py
uitester/__init__.py
uitester/base.py
uitester/cli.py
uitester/element.py
uitester/tempCodeRunnerFile.py
uitester.egg-info/PKG-INFO
uitester.egg-info/SOURCES.txt
uitester.egg-info/dependency_links.txt
uitester.egg-info/entry_points.txt
uitester.egg-info/requires.txt
uitester.egg-info/top_level.txt
uitester.egg-info/zip-safe
uitester/common/__init__.py
uitester/common/data.py
uitester/common/decorator.py
uitester/common/logger.py
uitester/common/metaclass.py