Metadata-Version: 1.1
Name: uitester
Version: 0.3
Summary: package description.
Home-page: http://gaianote.github.io/
Author: gaianote311
Author-email: gaianote311@gmail.com
License: MIT
Keywords: web ui autotest python package
Platform: UNKNOWN
Classifier: License :: OSI Approved :: MIT License
Classifier: Programming Language :: Python
Classifier: Intended Audience :: Developers
Classifier: Operating System :: OS Independent
